{
  "world_id": "medici",
  "world_name": "Medici Crash Island",
  "theme": "healer-isle",
  "tech_level": "pre-industrial",
  "magic_level": "high",
  "is_hub": false,
  "description": "Medici healer's island. Site of the original Medici ship crash. Males wear taboo body-coverings per local custom. Healing-bloodline majority. Visitors are screened for fire-bloodline ancestry on entry.",
  "culture_id": "medici",
  "faction_id": "medici",
  "rule_modulators": {
    "combatLethality": 0.8,
    "refusalSensitivity": 1.0,
    "questDensity": 1.2,
    "weatherIntensity": 0.9,
    "climate": { "temperature": 24, "humidity": 75, "airQuality": 0.97, "wind": "low" }
  },
  "anchors": [
    { "id": "medici_crash_site",  "name": "The Crash Site",      "x": 0,   "z": 0,   "kind": "lore_anchor" },
    { "id": "medici_stillrooms",  "name": "Medici Stillrooms",   "x": 40,  "z": 30,  "kind": "trade_zone" }
  ],
  "spawn_position": { "x": 10, "z": 5 },
  "primary_currencies": ["concord_coin"],
  "preferred_visit_order": 10
}
