{
  "mode": "applied",
  "total": 232,
  "applied": 226,
  "skipped": 6,
  "skipReasons": {
    "no_recent_mine_card": 6
  },
  "appliedFiles": [
    "app/lenses/accounting/page.tsx",
    "app/lenses/admin/page.tsx",
    "app/lenses/affect/page.tsx",
    "app/lenses/agents/page.tsx",
    "app/lenses/agriculture/page.tsx",
    "app/lenses/all/page.tsx",
    "app/lenses/alliance/page.tsx",
    "app/lenses/analytics/page.tsx",
    "app/lenses/animation/page.tsx",
    "app/lenses/anon/page.tsx",
    "app/lenses/answers/page.tsx",
    "app/lenses/app-maker/page.tsx",
    "app/lenses/ar/page.tsx",
    "app/lenses/art/page.tsx",
    "app/lenses/artistry/page.tsx",
    "app/lenses/astronomy/page.tsx",
    "app/lenses/atlas/page.tsx",
    "app/lenses/attention/page.tsx",
    "app/lenses/audit/page.tsx",
    "app/lenses/automotive/page.tsx",
    "app/lenses/aviation/page.tsx",
    "app/lenses/billing/page.tsx",
    "app/lenses/bio/page.tsx",
    "app/lenses/black-market/page.tsx",
    "app/lenses/board/page.tsx",
    "app/lenses/bounties/page.tsx",
    "app/lenses/bridge/page.tsx",
    "app/lenses/byo-keys/page.tsx",
    "app/lenses/calendar/page.tsx",
    "app/lenses/carpentry/page.tsx",
    "app/lenses/chem/page.tsx",
    "app/lenses/classroom/page.tsx",
    "app/lenses/code/page.tsx",
    "app/lenses/code-quality/page.tsx",
    "app/lenses/cognition/page.tsx",
    "app/lenses/cognitive-replay/page.tsx",
    "app/lenses/collab/page.tsx",
    "app/lenses/command-center/page.tsx",
    "app/lenses/commonsense/page.tsx",
    "app/lenses/construction/page.tsx",
    "app/lenses/consulting/page.tsx",
    "app/lenses/cooking/page.tsx",
    "app/lenses/council/page.tsx",
    "app/lenses/crafting/page.tsx",
    "app/lenses/creative/page.tsx",
    "app/lenses/creative-writing/page.tsx",
    "app/lenses/creator/page.tsx",
    "app/lenses/cri/page.tsx",
    "app/lenses/crisis-ops/page.tsx",
    "app/lenses/crypto/page.tsx",
    "app/lenses/custom/page.tsx",
    "app/lenses/daily/page.tsx",
    "app/lenses/database/page.tsx",
    "app/lenses/death-insurance/page.tsx",
    "app/lenses/debate/page.tsx",
    "app/lenses/debug/page.tsx",
    "app/lenses/defense/page.tsx",
    "app/lenses/deities/page.tsx",
    "app/lenses/desert/page.tsx",
    "app/lenses/disputes/page.tsx",
    "app/lenses/diy/page.tsx",
    "app/lenses/docs/page.tsx",
    "app/lenses/dreams/page.tsx",
    "app/lenses/dtus/page.tsx",
    "app/lenses/dx-platform/page.tsx",
    "app/lenses/eco/page.tsx",
    "app/lenses/electrical/page.tsx",
    "app/lenses/emergency-services/page.tsx",
    "app/lenses/energy/page.tsx",
    "app/lenses/engineering/page.tsx",
    "app/lenses/entity/page.tsx",
    "app/lenses/ethics/page.tsx",
    "app/lenses/event-timeline/page.tsx",
    "app/lenses/events/page.tsx",
    "app/lenses/expedition-journal/page.tsx",
    "app/lenses/experience/page.tsx",
    "app/lenses/expert-mode/page.tsx",
    "app/lenses/export/page.tsx",
    "app/lenses/fashion/page.tsx",
    "app/lenses/federation/page.tsx",
    "app/lenses/feed/page.tsx",
    "app/lenses/film-studios/page.tsx",
    "app/lenses/finance/page.tsx",
    "app/lenses/fitness/page.tsx",
    "app/lenses/food/page.tsx",
    "app/lenses/forecast/page.tsx",
    "app/lenses/forestry/page.tsx",
    "app/lenses/forge/page.tsx",
    "app/lenses/fork/page.tsx",
    "app/lenses/forum/page.tsx",
    "app/lenses/foundry/page.tsx",
    "app/lenses/fractal/page.tsx",
    "app/lenses/gallery/page.tsx",
    "app/lenses/game/page.tsx",
    "app/lenses/game-design/page.tsx",
    "app/lenses/genesis/page.tsx",
    "app/lenses/geology/page.tsx",
    "app/lenses/ghost-tracker/page.tsx",
    "app/lenses/global/page.tsx",
    "app/lenses/goals/page.tsx",
    "app/lenses/goddess/page.tsx",
    "app/lenses/graph/page.tsx",
    "app/lenses/grounding/page.tsx",
    "app/lenses/history/page.tsx",
    "app/lenses/home-improvement/page.tsx",
    "app/lenses/household/page.tsx",
    "app/lenses/hr/page.tsx",
    "app/lenses/hvac/page.tsx",
    "app/lenses/hypothesis/page.tsx",
    "app/lenses/import/page.tsx",
    "app/lenses/inference/page.tsx",
    "app/lenses/ingest/page.tsx",
    "app/lenses/inheritance/page.tsx",
    "app/lenses/insurance/page.tsx",
    "app/lenses/integrations/page.tsx",
    "app/lenses/invariant/page.tsx",
    "app/lenses/kingdoms/page.tsx",
    "app/lenses/lab/page.tsx",
    "app/lenses/landscaping/page.tsx",
    "app/lenses/lattice/page.tsx",
    "app/lenses/law/page.tsx",
    "app/lenses/law-enforcement/page.tsx",
    "app/lenses/legacy/page.tsx",
    "app/lenses/legal/page.tsx",
    "app/lenses/linguistics/page.tsx",
    "app/lenses/lock/page.tsx",
    "app/lenses/logistics/page.tsx",
    "app/lenses/maker/page.tsx",
    "app/lenses/manufacturing/page.tsx",
    "app/lenses/market/page.tsx",
    "app/lenses/marketing/page.tsx",
    "app/lenses/marketplace/page.tsx",
    "app/lenses/markets/page.tsx",
    "app/lenses/masonry/page.tsx",
    "app/lenses/materials/page.tsx",
    "app/lenses/math/page.tsx",
    "app/lenses/meditation/page.tsx",
    "app/lenses/mental-health/page.tsx",
    "app/lenses/mentorship/page.tsx",
    "app/lenses/mesh/page.tsx",
    "app/lenses/message/page.tsx",
    "app/lenses/meta/page.tsx",
    "app/lenses/metacognition/page.tsx",
    "app/lenses/metalearning/page.tsx",
    "app/lenses/mining/page.tsx",
    "app/lenses/ml/page.tsx",
    "app/lenses/music/page.tsx",
    "app/lenses/neuro/page.tsx",
    "app/lenses/news/page.tsx",
    "app/lenses/nonprofit/page.tsx",
    "app/lenses/observe/page.tsx",
    "app/lenses/ocean/page.tsx",
    "app/lenses/offline/page.tsx",
    "app/lenses/ops/page.tsx",
    "app/lenses/organ/page.tsx",
    "app/lenses/paper/page.tsx",
    "app/lenses/parenting/page.tsx",
    "app/lenses/personas/page.tsx",
    "app/lenses/pets/page.tsx",
    "app/lenses/pharmacy/page.tsx",
    "app/lenses/philosophy/page.tsx",
    "app/lenses/photography/page.tsx",
    "app/lenses/physics/page.tsx",
    "app/lenses/platform/page.tsx",
    "app/lenses/plumbing/page.tsx",
    "app/lenses/podcast/page.tsx",
    "app/lenses/poetry/page.tsx",
    "app/lenses/privacy/page.tsx",
    "app/lenses/productivity/page.tsx",
    "app/lenses/projects/page.tsx",
    "app/lenses/psyops/page.tsx",
    "app/lenses/quantum/page.tsx",
    "app/lenses/questmarket/page.tsx",
    "app/lenses/queue/page.tsx",
    "app/lenses/realestate/page.tsx",
    "app/lenses/reasoning/page.tsx",
    "app/lenses/reflection/page.tsx",
    "app/lenses/repos/page.tsx",
    "app/lenses/research/page.tsx",
    "app/lenses/resonance/page.tsx",
    "app/lenses/retail/page.tsx",
    "app/lenses/robotics/page.tsx",
    "app/lenses/root/page.tsx",
    "app/lenses/sandbox/page.tsx",
    "app/lenses/schema/page.tsx",
    "app/lenses/science/page.tsx",
    "app/lenses/security/page.tsx",
    "app/lenses/self/page.tsx",
    "app/lenses/sentinel/page.tsx",
    "app/lenses/services/page.tsx",
    "app/lenses/settings/page.tsx",
    "app/lenses/sim/page.tsx",
    "app/lenses/society/page.tsx",
    "app/lenses/space/page.tsx",
    "app/lenses/sponsorship/page.tsx",
    "app/lenses/sports/page.tsx",
    "app/lenses/srs/page.tsx",
    "app/lenses/staking/page.tsx",
    "app/lenses/studio/page.tsx",
    "app/lenses/sub-worlds/page.tsx",
    "app/lenses/suffering/page.tsx",
    "app/lenses/supplychain/page.tsx",
    "app/lenses/sync/page.tsx",
    "app/lenses/system/page.tsx",
    "app/lenses/telecommunications/page.tsx",
    "app/lenses/temporal/page.tsx",
    "app/lenses/thread/page.tsx",
    "app/lenses/tick/page.tsx",
    "app/lenses/timeline/page.tsx",
    "app/lenses/tools/page.tsx",
    "app/lenses/tournaments/page.tsx",
    "app/lenses/trades/page.tsx",
    "app/lenses/transfer/page.tsx",
    "app/lenses/travel/page.tsx",
    "app/lenses/understanding/page.tsx",
    "app/lenses/urban-planning/page.tsx",
    "app/lenses/ux-suite/page.tsx",
    "app/lenses/veterinary/page.tsx",
    "app/lenses/voice/page.tsx",
    "app/lenses/vote/page.tsx",
    "app/lenses/wallet/page.tsx",
    "app/lenses/welding/page.tsx",
    "app/lenses/wellness/page.tsx",
    "app/lenses/whiteboard/page.tsx",
    "app/lenses/world-creator/page.tsx",
    "app/lenses/worldmodel/page.tsx"
  ]
}