{
  "contracts": [
    {
      "_derived": true,
      "domain": "companion",
      "fuzz_cases": [],
      "inputs": {},
      "invariants": [
        "output !== null && output !== undefined",
        "typeof output === 'object'",
        "(typeof output.ok === 'boolean') || (output !== null && typeof output === 'object')"
      ],
      "macro_id": "companion.feed",
      "name": "feed"
    },
    {
      "_derived": true,
      "domain": "companion",
      "fuzz_cases": [],
      "inputs": {},
      "invariants": [
        "output !== null && output !== undefined",
        "typeof output === 'object'",
        "(typeof output.ok === 'boolean') || (output !== null && typeof output === 'object')"
      ],
      "macro_id": "companion.notification-add",
      "name": "notification-add"
    },
    {
      "_derived": true,
      "domain": "companion",
      "fuzz_cases": [],
      "inputs": {},
      "invariants": [
        "output !== null && output !== undefined",
        "typeof output === 'object'",
        "(typeof output.ok === 'boolean') || (output !== null && typeof output === 'object')"
      ],
      "macro_id": "companion.notification-mark-read",
      "name": "notification-mark-read"
    },
    {
      "_derived": true,
      "domain": "companion",
      "fuzz_cases": [],
      "inputs": {},
      "invariants": [
        "output !== null && output !== undefined",
        "typeof output === 'object'",
        "(typeof output.ok === 'boolean') || (output !== null && typeof output === 'object')"
      ],
      "macro_id": "companion.notifications-list",
      "name": "notifications-list"
    },
    {
      "_derived": true,
      "domain": "companion",
      "fuzz_cases": [],
      "inputs": {},
      "invariants": [
        "output !== null && output !== undefined",
        "typeof output === 'object'",
        "(typeof output.ok === 'boolean') || (output !== null && typeof output === 'object')"
      ],
      "macro_id": "companion.overnight-summary",
      "name": "overnight-summary"
    },
    {
      "_derived": true,
      "domain": "companion",
      "fuzz_cases": [],
      "inputs": {},
      "invariants": [
        "output !== null && output !== undefined",
        "typeof output === 'object'",
        "(typeof output.ok === 'boolean') || (output !== null && typeof output === 'object')"
      ],
      "macro_id": "companion.push-prefs-get",
      "name": "push-prefs-get"
    },
    {
      "_derived": true,
      "domain": "companion",
      "fuzz_cases": [],
      "inputs": {},
      "invariants": [
        "output !== null && output !== undefined",
        "typeof output === 'object'",
        "(typeof output.ok === 'boolean') || (output !== null && typeof output === 'object')"
      ],
      "macro_id": "companion.push-prefs-set",
      "name": "push-prefs-set"
    }
  ],
  "domain": "companion",
  "generatedBy": "scripts/contracts/derive-contracts.mjs",
  "macroCount": 7
}
