{
  "contracts": [
    {
      "_derived": true,
      "domain": "crypto",
      "fuzz_cases": [],
      "inputs": {},
      "invariants": [
        "output !== null && output !== undefined",
        "typeof output === 'object'",
        "(typeof output.ok === 'boolean') || (output !== null && typeof output === 'object')"
      ],
      "macro_id": "crypto.list_mine",
      "name": "list_mine"
    },
    {
      "_derived": true,
      "domain": "crypto",
      "fuzz_cases": [],
      "inputs": {},
      "invariants": [
        "output !== null && output !== undefined",
        "typeof output === 'object'",
        "(typeof output.ok === 'boolean') || (output !== null && typeof output === 'object')"
      ],
      "macro_id": "crypto.live_price",
      "name": "live_price"
    },
    {
      "_derived": true,
      "domain": "crypto",
      "fuzz_cases": [],
      "inputs": {},
      "invariants": [
        "output !== null && output !== undefined",
        "typeof output === 'object'",
        "(typeof output.ok === 'boolean') || (output !== null && typeof output === 'object')"
      ],
      "macro_id": "crypto.live_top",
      "name": "live_top"
    },
    {
      "_derived": true,
      "domain": "crypto",
      "fuzz_cases": [],
      "inputs": {},
      "invariants": [
        "output !== null && output !== undefined",
        "typeof output === 'object'",
        "(typeof output.ok === 'boolean') || (output !== null && typeof output === 'object')"
      ],
      "macro_id": "crypto.recent_mine",
      "name": "recent_mine"
    }
  ],
  "domain": "crypto",
  "generatedBy": "scripts/contracts/derive-contracts.mjs",
  "macroCount": 4
}
