{
  "contracts": [
    {
      "_derived": true,
      "domain": "geology",
      "fuzz_cases": [],
      "inputs": {},
      "invariants": [
        "output !== null && output !== undefined",
        "typeof output === 'object'",
        "(typeof output.ok === 'boolean') || (output !== null && typeof output === 'object')"
      ],
      "macro_id": "geology.list_mine",
      "name": "list_mine"
    },
    {
      "_derived": true,
      "domain": "geology",
      "fuzz_cases": [],
      "inputs": {},
      "invariants": [
        "output !== null && output !== undefined",
        "typeof output === 'object'",
        "(typeof output.ok === 'boolean') || (output !== null && typeof output === 'object')"
      ],
      "macro_id": "geology.live_quakes_today",
      "name": "live_quakes_today"
    },
    {
      "_derived": true,
      "domain": "geology",
      "fuzz_cases": [],
      "inputs": {},
      "invariants": [
        "output !== null && output !== undefined",
        "typeof output === 'object'",
        "(typeof output.ok === 'boolean') || (output !== null && typeof output === 'object')"
      ],
      "macro_id": "geology.live_wiki_search",
      "name": "live_wiki_search"
    },
    {
      "_derived": true,
      "domain": "geology",
      "fuzz_cases": [],
      "inputs": {},
      "invariants": [
        "output !== null && output !== undefined",
        "typeof output === 'object'",
        "(typeof output.ok === 'boolean') || (output !== null && typeof output === 'object')"
      ],
      "macro_id": "geology.live_wiki_summary",
      "name": "live_wiki_summary"
    },
    {
      "_derived": true,
      "domain": "geology",
      "fuzz_cases": [],
      "inputs": {},
      "invariants": [
        "output !== null && output !== undefined",
        "typeof output === 'object'",
        "(typeof output.ok === 'boolean') || (output !== null && typeof output === 'object')"
      ],
      "macro_id": "geology.recent_mine",
      "name": "recent_mine"
    }
  ],
  "domain": "geology",
  "generatedBy": "scripts/contracts/derive-contracts.mjs",
  "macroCount": 5
}
