{
  "contracts": [
    {
      "_derived": true,
      "domain": "graph",
      "fuzz_cases": [],
      "inputs": {},
      "invariants": [
        "output !== null && output !== undefined",
        "typeof output === 'object'",
        "(typeof output.ok === 'boolean') || (output !== null && typeof output === 'object')"
      ],
      "macro_id": "graph.forceGraph",
      "name": "forceGraph"
    },
    {
      "_derived": true,
      "domain": "graph",
      "fuzz_cases": [],
      "inputs": {},
      "invariants": [
        "output !== null && output !== undefined",
        "typeof output === 'object'",
        "(typeof output.ok === 'boolean') || (output !== null && typeof output === 'object')"
      ],
      "macro_id": "graph.query",
      "name": "query"
    },
    {
      "_derived": true,
      "domain": "graph",
      "fuzz_cases": [],
      "inputs": {},
      "invariants": [
        "output !== null && output !== undefined",
        "typeof output === 'object'",
        "(typeof output.ok === 'boolean') || (output !== null && typeof output === 'object')"
      ],
      "macro_id": "graph.visualData",
      "name": "visualData"
    }
  ],
  "domain": "graph",
  "generatedBy": "scripts/contracts/derive-contracts.mjs",
  "macroCount": 3
}
